BioLizardStylePython/__init__.py
BioLizardStylePython/l_viridis.py
BioLizardStylePython/l_viridis1.py
BioLizardStylePython/lizard_style.mplstyle
BioLizardStylePython/plotly_template.py
BioLizardStylePython/utils.py
BioLizardStylePython/logo/BiolizardLogo.png
biolizardstylepython-2.0.1.dist-info/METADATA
biolizardstylepython-2.0.1.dist-info/WHEEL
biolizardstylepython-2.0.1.dist-info/licenses/LICENSE
biolizardstylepython-2.0.1.dist-info/RECORD
