Metadata-Version: 2.4
Name: BioLizardStylePython
Version: 2.0.1
Summary: Enhance plots with the signature Biolizard aesthetic for matplotlib and seaborn.
Project-URL: Homepage, https://github.com/lizard-bio/nature-grade-visualization-playground/tree/main
Author: Robbe Neirynck
Author-email: BioLizard <contact@lizard.bio>, Aniko Meijer <aniko.meijer@lizard.bio>, Artuur Couckuyt <artuur.couckuyt@lizard.bio>
Maintainer-email: Alexander Koch <alexander.koch@lizard.bio>, Aniko Meijer <aniko.meijer@lizard.bio>, Artuur Couckuyt <artuur.couckuyt@lizard.bio>
License-File: LICENSE
Classifier: License :: OSI Approved :: MIT License
Classifier: Operating System :: OS Independent
Classifier: Programming Language :: Python :: 3
Requires-Python: >=3.9
Requires-Dist: colorspace>=0.4.0
Requires-Dist: font-lato>=0.1.0
Requires-Dist: fonts>=0.0.3
Requires-Dist: matplotlib>=3.7.1
Requires-Dist: pillow>=9.4.0
Requires-Dist: plotly>=5.20.0
Requires-Dist: seaborn>=0.13.2
Requires-Dist: setuptools>=78.1.0
Provides-Extra: dev
Requires-Dist: numpy>=2.2.4; extra == 'dev'
Requires-Dist: pytest>=8.3.5; extra == 'dev'
